Metadata-Version: 2.1
Name: panik-core
Version: 0.0.2
Summary: THE python graphical library
Home-page: UNKNOWN
Author: Panik Core Studios
License: UNKNOWN
Keywords: python,graphics,game,gui,gamedev,gameengine
Platform: UNKNOWN
Classifier: Development Status :: 4 - Beta
Classifier: Intended Audience :: Developers
Classifier: Programming Language :: Python :: 3
Classifier: Operating System :: Unix
Classifier: Operating System :: MacOS :: MacOS X
Classifier: Operating System :: Microsoft :: Windows
